{"Users":{"033gCniiYUPDCjff1o916T7YBqQ2":{"access_level":"user","banned":"nope","classDiv":"Division1","credit_points":"50","department":"B. Tech. Civil Engineering","depindex":"2","email":"neerajpawale4@gmail.com","name":"Neeraj Pawale","rollNo":"S1032181382","terms":"Checked","uid":"033gCniiYUPDCjff1o916T7YBqQ2","year":"2"},"ZyW9WxjrjpVnsFoFlqz8JTy5WHla":{"bountyscore":100,"credit_points":50,"frombounty":true,"thebountyhunt":{"currLevel":1,"ques":[null,{"ans":"123"}]}}},"thebountyhunt":{"leaderboards":[null,{"Name":"User1","Score":100}],"questions":[null,{"ans":"123","ques":["He had","Mangoes"]}]}}